setup.py
anonymity/__init__.py
anonymity/metrics/__init__.py
anonymity/metrics/data_utility_metrics.py
anonymity/metrics/efficiency_metrics.py
anonymity/tools/__init__.py
anonymity/tools/_k_anonymity.py
anonymity/tools/_l_diversity.py
anonymity/tools/_t_closeness.py
anonymity/tools/utils_k_anon/__init__.py
anonymity/tools/utils_k_anon/utils_k_anonymity.py
build/lib/anonymity/__init__.py
build/lib/anonymity/metrics/__init__.py
build/lib/anonymity/metrics/data_utility_metrics.py
build/lib/anonymity/metrics/efficiency_metrics.py
build/lib/anonymity/tools/__init__.py
build/lib/anonymity/tools/_k_anonymity.py
build/lib/anonymity/tools/_l_diversity.py
build/lib/anonymity/tools/_t_closeness.py
build/lib/anonymity/tools/utils_k_anon/__init__.py
build/lib/anonymity/tools/utils_k_anon/utils_k_anonymity.py
docs/source/conf.py
venv/Lib/site-packages/_virtualenv.py
venv/Lib/site-packages/py.py
venv/Lib/site-packages/six.py
venv/Lib/site-packages/typing_extensions.py
venv/Lib/site-packages/_distutils_hack/__init__.py
venv/Lib/site-packages/_distutils_hack/override.py
venv/Lib/site-packages/_pytest/__init__.py
venv/Lib/site-packages/_pytest/_argcomplete.py
venv/Lib/site-packages/_pytest/_version.py
venv/Lib/site-packages/_pytest/cacheprovider.py
venv/Lib/site-packages/_pytest/capture.py
venv/Lib/site-packages/_pytest/compat.py
venv/Lib/site-packages/_pytest/debugging.py
venv/Lib/site-packages/_pytest/deprecated.py
venv/Lib/site-packages/_pytest/doctest.py
venv/Lib/site-packages/_pytest/faulthandler.py
venv/Lib/site-packages/_pytest/fixtures.py
venv/Lib/site-packages/_pytest/freeze_support.py
venv/Lib/site-packages/_pytest/helpconfig.py
venv/Lib/site-packages/_pytest/hookspec.py
venv/Lib/site-packages/_pytest/junitxml.py
venv/Lib/site-packages/_pytest/legacypath.py
venv/Lib/site-packages/_pytest/logging.py
venv/Lib/site-packages/_pytest/main.py
venv/Lib/site-packages/_pytest/monkeypatch.py
venv/Lib/site-packages/_pytest/nodes.py
venv/Lib/site-packages/_pytest/nose.py
python_anonymity-0.0.1.dist-info/METADATA
python_anonymity-0.0.1.dist-info/WHEEL
python_anonymity-0.0.1.dist-info/licenses/LICENSE
python_anonymity-0.0.1.dist-info/RECORD
