Metadata-Version: 2.1
Name: python-anonymity
Version: 0.0.1
Summary: Anonymity library for python
Project-URL: Homepage, https://github.com/IFCA/python-anonymity/tree/main
Project-URL: Read the docs, https://python-anonymity.readthedocs.io/en/latest/
Author-email: "esmeralda.madrazo" <esme21100@gmail.com>
License:                                  Apache License
License-File: LICENSE
Classifier: License :: OSI Approved :: MIT License
Classifier: Operating System :: OS Independent
Classifier: Programming Language :: Python :: 3
Requires-Python: >=3.7
